slate/__init__.py
slate/frontmatter.py
slate/loader.py
slate/main.py
slate/navigation.py
slate/parse.py
slate/rebuild.py
slate/render.py
slate/rss.py
slate/scaffold.py
slate/site.py
slate/toc_footnotes.py
slate_md-0.2.7.dist-info/METADATA
slate_md-0.2.7.dist-info/WHEEL
slate_md-0.2.7.dist-info/entry_points.txt
slate_md-0.2.7.dist-info/licenses/LICENSE
slate_md-0.2.7.dist-info/RECORD
