Metadata-Version: 2.4
Name: slate-md
Version: 0.2.7
Summary: A lightweight Python CLI tool for converting Markdown to accessible static HTML pages, Gemtext, and Gophermaps.
License-File: LICENSE
Author: Hailey Welsh
Author-email: dev@haileywelsh.me
Requires-Python: >=3.14
Classifier: Programming Language :: Python :: 3
Classifier: Programming Language :: Python :: 3.14
Requires-Dist: beautifulsoup4 (>=4.14.2,<5.0.0)
Requires-Dist: jinja2 (>=3.1.6,<4.0.0)
Requires-Dist: linkify-it-py (>=2.0.3,<3.0.0)
Requires-Dist: markdown-it-py[plugins] (>=4.0.0,<5.0.0)
Requires-Dist: pyyaml (>=6.0.3,<7.0.0)
Requires-Dist: rich (>=14.2.0,<15.0.0)
